cra_helper/__init__.py
cra_helper/asset_manifest.py
cra_helper/context_processors.py
cra_helper/finders.py
cra_helper/handlers.py
cra_helper/logging.py
cra_helper/server_check.py
cra_helper/storage.py
cra_helper/views.py
cra_helper/management/__init__.py
cra_helper/management/commands/__init__.py
cra_helper/management/commands/runserver.py
cra_helper/tests/__init__.py
cra_helper/tests/test_asset_manifest.py
cra_helper/tests/test_context_processors.py
cra_helper/tests/test_handlers.py
cra_helper/tests/test_package_json_homepage.py
cra_helper/tests/test_server_check.py
django_cra_helper-2.0.1.dist-info/LICENSE.txt
django_cra_helper-2.0.1.dist-info/METADATA
django_cra_helper-2.0.1.dist-info/WHEEL
django_cra_helper-2.0.1.dist-info/top_level.txt
django_cra_helper-2.0.1.dist-info/RECORD
