Metadata-Version: 2.1
Name: django-cra-helper
Version: 2.0.1
Summary: The missing piece of the Django + React puzzle
Home-page: https://github.com/MasterKale/django-cra-helper
Author: Matthew Miller
Author-email: matthew@millerti.me
License: MIT
Keywords: django react create-react-app integrate
Platform: UNKNOWN
Classifier: Development Status :: 5 - Production/Stable
Classifier: Intended Audience :: Developers
Classifier: License :: OSI Approved :: MIT License
Classifier: Programming Language :: Python :: 3
Requires-Dist: django-proxy (>=1.2.1)
